memtrace/ud.py
memtrace/memtrace.ipynb
memtrace/notebook.py
memtrace/format.py
memtrace/native.py
memtrace/analysis.py
memtrace/cli.py
memtrace/_memtrace.cpython-36m-arm-linux-gnueabihf.so
memtrace/tracer.py
memtrace/stats.py
memtrace/interval_tree.py
memtrace/__init__.py
memtrace/trace.py
memtrace/taint.py
memtrace/symbolizer.py
memtrace/tracer/Linux-arm/libexec/valgrind/memtrace-arm-linux
memtrace/tracer/Linux-arm/libexec/valgrind/vgpreload_core-arm-linux.so
memtrace/tracer/Linux-arm/bin/valgrind
memtrace-0.2.6.dist-info/WHEEL
memtrace-0.2.6.dist-info/RECORD
memtrace-0.2.6.dist-info/top_level.txt
memtrace-0.2.6.dist-info/entry_points.txt
memtrace-0.2.6.dist-info/METADATA
