Metadata-Version: 2.1
Name: memtrace
Version: 0.2.6
Summary: Valgrind tool for tracing memory accesses
Home-page: https://github.com/mephi42/memtrace
Author: mephi42
Author-email: mephi42@gmail.com
License: UNKNOWN
Platform: UNKNOWN
Classifier: Programming Language :: Python :: 3
Classifier: License :: OSI Approved :: GNU General Public License v2 (GPLv2)
Classifier: Operating System :: OS Independent
Requires-Python: >=3.6
Requires-Dist: click
Requires-Dist: sortedcontainers
Requires-Dist: dataclasses; python_version < "3.7"
